FilterHTML.py
setup.py
FilterHTML.egg-info/PKG-INFO
FilterHTML.egg-info/SOURCES.txt
FilterHTML.egg-info/dependency_links.txt
FilterHTML.egg-info/top_level.txt