Metadata-Version: 1.0
Name: FilterHTML
Version: 0.1.1
Summary: FilterHTML: A whitelisting HTML filter
Home-page: http://dcollien.github.com/FilterHTML/
Author: David Collien
Author-email: me@dcollien.com
License: MIT
Platform: any
